README.rst
setup.py
printargs/__init__.py
printargs/print_args.py
printargs.egg-info/PKG-INFO
printargs.egg-info/SOURCES.txt
printargs.egg-info/dependency_links.txt
printargs.egg-info/top_level.txt