Metadata-Version: 1.1
Name: printargs
Version: 1.0.1
Summary: Show and print the content of argparse.Namespace (args) objects for debugging.
Home-page: https://bitbucket.org/HenningTimm/printargs
Author: Henning Timm
Author-email: henning.timm@tu-dortmund.de
License: MIT
Platform: UNKNOWN
Classifier: Development Status :: 5 - Production/Stable
Classifier: Environment :: Console
Classifier: Intended Audience :: Developers
Classifier: License :: OSI Approved :: MIT License
Classifier: Natural Language :: English
Classifier: Programming Language :: Python :: 2
Classifier: Programming Language :: Python :: 2.7
Classifier: Programming Language :: Python :: 3
Classifier: Programming Language :: Python :: 3.3
Classifier: Programming Language :: Python :: 3.4
Classifier: Programming Language :: Python :: 3.5
Classifier: Topic :: Software Development
